rtl/driver7seg.v
// -----------------------------------------------------------------------------
// Autor: Angel Terrones <aterrones@usb.ve>
// Modulo: Driver 7-segmentos
// -----------------------------------------------------------------------------
`default_nettype none
`timescale 1ns / 1ps

module driver7seg(
                  input wire       clk,
                  input wire       rst,
                  input wire       tick_display,
                  input wire [3:0] value,
                  input wire       off_display,
                  output reg [3:0] anodos,
                  output reg [7:0] segmentos
                  );
    //--------------------------------------------------------------------------
    reg [7:0] segment_ROM [0:15];

    initial begin
        segment_ROM[0]  = 8'h03;
        segment_ROM[1]  = 8'h9f;
        segment_ROM[2]  = 8'h25;
        segment_ROM[3]  = 8'h0d;
        segment_ROM[4]  = 8'h99;
        segment_ROM[5]  = 8'h49;
        segment_ROM[6]  = 8'h41;
        segment_ROM[7]  = 8'h1f;
        segment_ROM[8]  = 8'h01;
        segment_ROM[9]  = 8'h09;
        segment_ROM[10] = 8'h11;
        segment_ROM[11] = 8'hc1;
        segment_ROM[12] = 8'h63;
        segment_ROM[13] = 8'h85;
        segment_ROM[14] = 8'h61;
        segment_ROM[15] = 8'h71;
    end

    always @(posedge clk) begin
        if (rst)               anodos <= 4'b0001;
        else if (tick_display) anodos <= {anodos[2:0],anodos[3]};
    end

    always @(
        segment_ROM[0],
		segment_ROM[1], 
        segment_ROM[2], 
        segment_ROM[4],
        segment_ROM[5],
        segment_ROM[6],
        segment_ROM[7],
        segment_ROM[8],
        segment_ROM[9],
        segment_ROM[10],
        segment_ROM[11],
        segment_ROM[12],
        segment_ROM[13],
        segment_ROM[14],
        segment_ROM[15],
		off_display,
		value) begin
		  
        if (off_display) begin
            segmentos = 8'hff;
        end else begin
            segmentos = segment_ROM[value];
        end
    end
    //--------------------------------------------------------------------------
endmodule
// EOF

rtl/clk_div.v
// -----------------------------------------------------------------------------
// Autor: Angel Terrones <aterrones@usb.ve>
// Modulo: clock divider
// -----------------------------------------------------------------------------
`default_nettype none
`timescale 1ns / 1ps

module clk_div #(
                 parameter CLK_XTAL    = 50000000,
                 parameter CLK_DISPLAY = 240,
                 parameter CLK_BANNER  = 1
                 )(
                   input wire clk,
                   input wire rst,
                   output reg tick_display,
                   output reg tick_banner
                   );
    //--------------------------------------------------------------------------
    //WARNING: (CLK_DISPLAY/CLK_BANNER) % 4 == 0

    //dos contadores para crear un clock de 1 hz (tick_banner) y otro de 60 hz (tick_display)
    reg [25:0] cnt1, cnt2;

    always @(posedge clk) begin
      
      //cuando el contador llega a 50 Mhz/1 se resetea y al mismo tiempo hace que tickbanner valga 1, inmediatamente despues tickbaner vale cero
      //hasta que ocurra la condicion de nuevo. Esto transforma a tickbanner a 1 hz. (recuerda que el clock es de 50Mhz por segundo)
      if(~rst)begin      

        if(cnt1 == CLK_XTAL/CLK_BANNER) begin
          cnt1 <= 0;
        end else begin
          cnt1 <= cnt1+1;
        end
      
        tick_banner <= (cnt1 == CLK_XTAL/CLK_BANNER)? 1:0;

        //cuando el contador llega a 50 Mhz/60 se resetea y al mismo tiempo hace que tickdisplay valga 1, inmediatamente despues tickdisplay
        //vale cero hasta que ocurra la condicion de nuevo. Esto transforma a tickdisplay a 60 hz, 60 veces por segundo.
        //(recuerda que el clock es de 50Mhz por segundo).    
        if(cnt2 == CLK_XTAL/CLK_DISPLAY) begin
          cnt2 <= 0;
        end else begin
          cnt2 <= cnt2+1;
        end
      
        tick_display <= (cnt2 == CLK_XTAL/CLK_DISPLAY)? 1:0;

        //Si presionan reset, reinicia los contadores y baja las señales de tickbanner y tickdisplay    
      end else begin
        cnt1 <= 0;
        cnt2<=0;
        tick_banner <= 0;
        tick_display <= 0;
      end // end else
      
    end // always @(posedge clk)


    //--------------------------------------------------------------------------
endmodule // clk_div
// EOF

rtl/banner.v
// -----------------------------------------------------------------------------
// Autor: Angel Terrones <aterrones@usb.ve>
// Modulo: Driver 7-segmentos
// -----------------------------------------------------------------------------
`default_nettype none
`timescale 1ns / 1ps

module banner #(
                parameter CLK_XTAL    = 50000000,
                parameter CLK_DISPLAY = 240,
                parameter CLK_BANNER  = 1
                )(
                  input wire        clk,
                  input wire        rst,
                  output wire [3:0] anodos,
                  output wire [7:0] segmentos,
                  output reg        shift
                  );
    //--------------------------------------------------------------------------
    // WARNING: READ ONLY
    /*AUTOWIRE*/
    // Beginning of automatic wires (for undeclared instantiated-module outputs)
    wire                tick_banner;            // From clkdiv of clk_div.v
    wire                tick_display;           // From clkdiv of clk_div.v
    // End of automatics
    reg [3:0] number2show = 4'h0;
    reg       off_display;
    // ---------------------------------

    
    //para shiftear los estados del anodo y banner
    reg [4:0] state_b = 5'b0, nextstate_b = 5'b0;
    reg [1:0] state_a = 2'b0, nextstate_a = 2'b0;

    
    //Definicion de cada estado del banner
    parameter s0 = 5'b00000;
    parameter s1 = 5'b00001;
    parameter s2 = 5'b00010;
    parameter s3 = 5'b00011;
    parameter s4 = 5'b00100;
    parameter s5 = 5'b00101;
    parameter s6 = 5'b00110;
    parameter s7 = 5'b00111;
    parameter s8 = 5'b01000;
    parameter s9 = 5'b01001;
    parameter s10 = 5'b01010;
    parameter s11 = 5'b01011;
    parameter s12 = 5'b01100;
    parameter s13 = 5'b01101;
    parameter s14 = 5'b01110;
    parameter s15 = 5'b01111;
    parameter s16 = 5'b10000;
    parameter s17 = 5'b10001;
    parameter s18 = 5'b10010;
    parameter s19 = 5'b10011;

    //Definicion de cada estado del anodo
    parameter a0 = 2'b00;
    parameter a1 = 2'b01;
    parameter a2 = 2'b10;
    parameter a3 = 2'b11;

    //para la simulacion
    always @(*) begin
    	shift = tick_banner;
    end
    /*
    //cada flanco positivo del banner, cambia de estado el banner.
    always @(posedge tick_banner) begin
    	state_b <= nextstate_b;
    end*/

    //en cada estado del banner, nextstate_b apunta al siguiente estado del banner
    always @(*) begin

    	if(~rst) begin
    		
    		case(state_b) 
    			s0: nextstate_b = s1;
        		s1: nextstate_b = s2;
        		s2: nextstate_b = s3;
        		s3: nextstate_b = s4;
        		s4: nextstate_b = s5;
        		s5: nextstate_b = s6;
        		s6: nextstate_b = s7;
        		s7: nextstate_b = s8;
        		s8: nextstate_b = s9;
        		s9: nextstate_b = s10;
        		s10: nextstate_b = s11;
        		s11: nextstate_b = s12;
        		s12: nextstate_b = s13;
        		s13: nextstate_b = s14;
        		s14: nextstate_b = s15;
        		s15: nextstate_b = s16;
        		s16: nextstate_b = s17;
        		s17: nextstate_b = s18;
        		s18: nextstate_b = s19;
        		s19: nextstate_b = s0;
        		default: nextstate_b = s0;
        	endcase // state_b

        end else begin
        	nextstate_b = s0;
        end // end else

    end

    /*//cada flanco positivo del display, se cambia de estado el display
    always @(posedge tick_display) begin
    	state_a <= nextstate_a;
    end*/

    //en cada estado de anado, nexstate_a apunta al siguiente estado del anodo
    always @(*) begin
    	
    	if(~rst) begin

    		case(state_a) 
        		a0: nextstate_a = a1;
        		a1: nextstate_a = a2;
        		a2: nextstate_a = a3;
        		a3: nextstate_a = a0;
      		endcase
      	
      	end else begin
      		nextstate_a = a0;
      	end // end else
    
    end // always(*)

    always @(posedge clk) begin
      
		if(~rst) begin // Si no resetean

			if(tick_banner)
        state_b <= nextstate_b;
      if(tick_display)
        state_a <= nextstate_a;

      case (state_b) 

				s0: case (state_a) 
						default off_display <= 1;  
        			endcase
       
        		s1: case (state_a)
        				a3: begin off_display <= 0; number2show <= 4'h0; end
        				default off_display <= 1;
        			endcase

        		s2: case (state_a) 
          				a3: begin off_display <= 0; number2show <= 4'h1; end 
          				a2: begin off_display <= 0; number2show <= 4'h0; end 
          				default off_display <= 1;
        			endcase

        		s3: case (state_a) 
          				a3: begin off_display <= 0; number2show <= 4'h2; end 
          				a2: begin off_display <= 0; number2show <= 4'h1; end 
          				a1: begin off_display <= 0; number2show <= 4'h0; end 
          				a0: off_display <= 1;
        			endcase

        		s4: case (state_a) 
          				a3: begin off_display <= 0; number2show <= 4'h3; end 
          				a2: begin off_display <= 0; number2show <= 4'h2; end 
          				a1: begin off_display <= 0; number2show <= 4'h1; end 
          				a0: begin off_display <= 0; number2show <= 4'h0; end 
        			endcase

        		s5: case (state_a) 
          				a3: begin off_display <= 0; number2show <= 4'h4; end 
          				a2: begin off_display <= 0; number2show <= 4'h3; end 
          				a1: begin off_display <= 0; number2show <= 4'h2; end 
          				a0: begin off_display <= 0; number2show <= 4'h1; end 
          			endcase

        		s6: case (state_a) 
          				a3: begin off_display <= 0; number2show <= 4'h5; end 
          				a2: begin off_display <= 0; number2show <= 4'h4; end 
          				a1: begin off_display <= 0; number2show <= 4'h3; end 
          				a0: begin off_display <= 0; number2show <= 4'h2; end 
          			endcase

        		s7: case (state_a) 
          				a3: begin off_display <= 0; number2show <= 4'h6; end 
          				a2: begin off_display <= 0; number2show <= 4'h5; end 
          				a1: begin off_display <= 0; number2show <= 4'h4; end 
          				a0: begin off_display <= 0; number2show <= 4'h3; end
          			endcase

        		s8: case (state_a) 
          				a3: begin off_display <= 0; number2show <= 4'h7; end 
          				a2: begin off_display <= 0; number2show <= 4'h6; end 
          				a1: begin off_display <= 0; number2show <= 4'h5; end 
          				a0: begin off_display <= 0; number2show <= 4'h4; end
          			endcase

        		s9: case (state_a) 
          				a3: begin off_display <= 0; number2show <= 4'h8; end 
          				a2: begin off_display <= 0; number2show <= 4'h7; end 
          				a1: begin off_display <= 0; number2show <= 4'h6; end 
	          			a0: begin off_display <= 0; number2show <= 4'h5; end
    	      		endcase

        		s10: case (state_a)
          				a3: begin off_display <= 0; number2show <= 4'h9; end 
          				a2: begin off_display <= 0; number2show <= 4'h8; end 
          				a1: begin off_display <= 0; number2show <= 4'h7; end 
	          			a0: begin off_display <= 0; number2show <= 4'h6; end
    	      		endcase

	        	s11: case (state_a)
   		       			a3: begin off_display <= 0; number2show <= 4'hA; end 
        	  			a2: begin off_display <= 0; number2show <= 4'h9; end 
          				a1: begin off_display <= 0; number2show <= 4'h8; end 
          				a0: begin off_display <= 0; number2show <= 4'h7; end
          			endcase 

        		s12: case (state_a)
          				a3: begin off_display <= 0; number2show <= 4'hB; end 
          				a2: begin off_display <= 0; number2show <= 4'hA; end 
          				a1: begin off_display <= 0; number2show <= 4'h9; end 
          				a0: begin off_display <= 0; number2show <= 4'h8; end
          			endcase

        		s13: case (state_a)
          				a3: begin off_display <= 0; number2show <= 4'hC; end 
          				a2: begin off_display <= 0; number2show <= 4'hB; end 
          				a1: begin off_display <= 0; number2show <= 4'hA; end 
          				a0: begin off_display <= 0; number2show <= 4'h9; end
          			endcase 

        		s14: case (state_a)
          				a3: begin off_display <= 0; number2show <= 4'hD; end 
          				a2: begin off_display <= 0; number2show <= 4'hC; end 
          				a1: begin off_display <= 0; number2show <= 4'hB; end 
          				a0: begin off_display <= 0; number2show <= 4'hA; end
          			endcase 

        		s15: case (state_a)
          				a3: begin off_display <= 0; number2show <= 4'hE; end 
          				a2: begin off_display <= 0; number2show <= 4'hD; end 
          				a1: begin off_display <= 0; number2show <= 4'hC; end 
          				a0: begin off_display <= 0; number2show <= 4'hB; end 
          			endcase 

        		s16: case (state_a)
          				a3: begin off_display <= 0; number2show <= 4'hF; end 
          				a2: begin off_display <= 0; number2show <= 4'hE; end 
          				a1: begin off_display <= 0; number2show <= 4'hD; end 
          				a0: begin off_display <= 0; number2show <= 4'hC; end
          			endcase 

				s17: case (state_a)
          				a3: off_display <= 1;
          				a2: begin off_display <= 0; number2show <= 4'hF; end 
          				a1: begin off_display <= 0; number2show <= 4'hE; end 
          				a0: begin off_display <= 0; number2show <= 4'hD; end
          			endcase 

        		s18: case (state_a)
          				a1: begin off_display <= 0; number2show <= 4'hF; end 
          				a0: begin off_display <= 0; number2show <= 4'hE; end 
          				default off_display <= 1;
          			endcase 

        		s19: case (state_a)
          				a0: begin off_display <= 0; number2show <= 4'hF; end 
          				default off_display <= 1;
          			endcase

        		default case (state_a) 
          					default off_display <= 1; 
        				endcase
        	endcase //end case (state_b)
     	
     	end else begin
     		off_display <= 1;
        state_b <= s0;
        state_a <= a0;
      	end
	 
    end // always @(posedge clk)


    // ---------------------------------
    // WARNING: READ ONLY
    // instanciacion
    clk_div #(/*AUTOINSTPARAM*/
              // Parameters
              .CLK_XTAL                 (CLK_XTAL),
              .CLK_DISPLAY              (CLK_DISPLAY),
              .CLK_BANNER               (CLK_BANNER)
              ) clkdiv (/*AUTOINST*/
                        // Outputs
                        .tick_display     (tick_display),
                        .tick_banner      (tick_banner),
                        // Inputs
                        .clk              (clk),
                        .rst              (rst));

    driver7seg driver(.value            (number2show[3:0]),
                      /*AUTOINST*/
                      // Outputs
                      .anodos           (anodos[3:0]),
                      .segmentos        (segmentos[7:0]),
                      // Inputs
                      .clk              (clk),
                      .rst              (rst),
                      .tick_display     (tick_display),
                      .off_display      (off_display));
    //--------------------------------------------------------------------------
endmodule
// EOF

test/tb_banner.v
/**
 * Autor: Ángel Terrones <aterrones@usb.ve>
 */
module tb_banner;

    reg clk;
    reg rst;
    wire [3:0] anodos;
    wire [7:0] segmentos;
    wire shift;

    initial begin
        $dumpfile("dut.vcd");
        $dumpvars(0, dut);
        $from_myhdl(
                    clk,
                    rst
                    );
        $to_myhdl(
                  anodos,
                  segmentos,
                  shift
                  );
    end

    banner #(600, 60, 5
             ) dut (
                    clk,
                    rst,
                    anodos,
                    segmentos,
                    shift
                    );
endmodule
// EOF

dut.vcd
$date
	Wed Nov 21 23:41:02 2018
$end
$version
	Icarus Verilog
$end
$timescale
	1ps
$end
$scope module tb_banner $end
$scope module dut $end
$var wire 1 ! clk $end
$var wire 1 " rst $end
$var wire 1 # tick_display $end
$var wire 1 $ tick_banner $end
$var wire 8 % segmentos [7:0] $end
$var wire 4 & anodos [3:0] $end
$var reg 2 ' nextstate_a [1:0] $end
$var reg 5 ( nextstate_b [4:0] $end
$var reg 4 ) number2show [3:0] $end
$var reg 1 * off_display $end
$var reg 1 + shift $end
$var reg 2 , state_a [1:0] $end
$var reg 5 - state_b [4:0] $end
$scope module clkdiv $end
$var wire 1 ! clk $end
$var wire 1 " rst $end
$var reg 26 . cnt1 [25:0] $end
$var reg 26 / cnt2 [25:0] $end
$var reg 1 $ tick_banner $end
$var reg 1 # tick_display $end
$upscope $end
$scope module driver $end
$var wire 1 ! clk $end
$var wire 1 * off_display $end
$var wire 1 " rst $end
$var wire 1 # tick_display $end
$var wire 4 0 value [3:0] $end
$var reg 4 1 anodos [3:0] $end
$var reg 8 2 segmentos [7:0] $end
$upscope $end
$upscope $end
$upscope $end
$enddefinitions $end
#0
$dumpvars
b11 2
bx 1
b0 0
bx /
bx .
b0 -
b0 ,
x+
x*
b0 )
b0 (
b0 '
bx &
b11 %
x$
x#
x"
x!
$end
#2
1"
0!
#5002
0+
b11111111 %
b11111111 2
0#
0$
b0 /
b0 .
b1 &
b1 1
1*
1!
#10002
0!
#15002
1!
#20002
0!
#25002
1!
#30002
0!
#35002
1!
#40002
0!
#45002
1!
#50002
b1 (
b1 '
0"
0!
#55002
b1 /
b1 .
1!
#60002
0!
#65002
b10 /
b10 .
1!
#70002
0!
#75002
b11 /
b11 .
1!
#80002
0!
#85002
b100 /
b100 .
1!
#90002
0!
#95002
b101 /
b101 .
1!
#100002
0!
#105002
b110 /
b110 .
1!
#110002
0!
#115002
b111 /
b111 .
1!
#120002
0!
#125002
b1000 /
b1000 .
1!
#130002
0!
#135002
b1001 /
b1001 .
1!
#140002
0!
#145002
b1010 /
b1010 .
1!
#150002
0!
#155002
b10 '
b1 ,
1#
b0 /
b1011 .
1!
#160002
0!
#165002
0#
b1 /
b1100 .
b10 &
b10 1
1!
#170002
0!
#175002
b10 /
b1101 .
1!
#180002
0!
#185002
b11 /
b1110 .
1!
#190002
0!
#195002
b100 /
b1111 .
1!
#200002
0!
#205002
b101 /
b10000 .
1!
#210002
0!
#215002
b110 /
b10001 .
1!
#220002
0!
#225002
b111 /
b10010 .
1!
#230002
0!
#235002
b1000 /
b10011 .
1!
#240002
0!
#245002
b1001 /
b10100 .
1!
#250002
0!
#255002
b1010 /
b10101 .
1!
#260002
0!
#265002
b11 '
b10 ,
1#
b0 /
b10110 .
1!
#270002
0!
#275002
b100 &
b100 1
0#
b1 /
b10111 .
1!
#280002
0!
#285002
b10 /
b11000 .
1!
#290002
0!
#295002
b11 /
b11001 .
1!
#300002
0!
#305002
b100 /
b11010 .
1!
#310002
0!
#315002
b101 /
b11011 .
1!
#320002
0!
#325002
b110 /
b11100 .
1!
#330002
0!
#335002
b111 /
b11101 .
1!
#340002
0!
#345002
b1000 /
b11110 .
1!
#350002
0!
#355002
b1001 /
b11111 .
1!
#360002
0!
#365002
b1010 /
b100000 .
1!
#370002
0!
#375002
b0 '
b11 ,
1#
b0 /
b100001 .
1!
#380002
0!
#385002
0#
b1 /
b100010 .
b1000 &
b1000 1
1!
#390002
0!
#395002
b10 /
b100011 .
1!
#400002
0!
#405002
b11 /
b100100 .
1!
#410002
0!
#415002
b100 /
b100101 .
1!
#420002
0!
#425002
b101 /
b100110 .
1!
#430002
0!
#435002
b110 /
b100111 .
1!
#440002
0!
#445002
b111 /
b101000 .
1!
#450002
0!
#455002
b1000 /
b101001 .
1!
#460002
0!
#465002
b1001 /
b101010 .
1!
#470002
0!
#475002
b1010 /
b101011 .
1!
#480002
0!
#485002
b1 '
b0 ,
1#
b0 /
b101100 .
1!
#490002
0!
#495002
b1 &
b1 1
0#
b1 /
b101101 .
1!
#500002
0!
#505002
b10 /
b101110 .
1!
#510002
0!
#515002
b11 /
b101111 .
1!
#520002
0!
#525002
b100 /
b110000 .
1!
#530002
0!
#535002
b101 /
b110001 .
1!
#540002
0!
#545002
b110 /
b110010 .
1!
#550002
0!
#555002
b111 /
b110011 .
1!
#560002
0!
#565002
b1000 /
b110100 .
1!
#570002
0!
#575002
b1001 /
b110101 .
1!
#580002
0!
#585002
b1010 /
b110110 .
1!
#590002
0!
#595002
b10 '
b1 ,
1#
b0 /
b110111 .
1!
#600002
0!
#605002
0#
b1 /
b111000 .
b10 &
b10 1
1!
#610002
0!
#615002
b10 /
b111001 .
1!
#620002
0!
#625002
b11 /
b111010 .
1!
#630002
0!
#635002
b100 /
b111011 .
1!
#640002
0!
#645002
b101 /
b111100 .
1!
#650002
0!
#655002
b110 /
b111101 .
1!
#660002
0!
#665002
b111 /
b111110 .
1!
#670002
0!
#675002
b1000 /
b111111 .
1!
#680002
0!
#685002
b1001 /
b1000000 .
1!
#690002
0!
#695002
b1010 /
b1000001 .
1!
#700002
0!
#705002
b11 '
b10 ,
1#
b0 /
b1000010 .
1!
#710002
0!
#715002
b100 &
b100 1
0#
b1 /
b1000011 .
1!
#720002
0!
#725002
b10 /
b1000100 .
1!
#730002
0!
#735002
b11 /
b1000101 .
1!
#740002
0!
#745002
b100 /
b1000110 .
1!
#750002
0!
#755002
b101 /
b1000111 .
1!
#760002
0!
#765002
b110 /
b1001000 .
1!
#770002
0!
#775002
b111 /
b1001001 .
1!
#780002
0!
#785002
b1000 /
b1001010 .
1!
#790002
0!
#795002
b1001 /
b1001011 .
1!
#800002
0!
#805002
b1010 /
b1001100 .
1!
#810002
0!
#815002
b0 '
b11 ,
1#
b0 /
b1001101 .
1!
#820002
0!
#825002
0#
b1 /
b1001110 .
b1000 &
b1000 1
1!
#830002
0!
#835002
b10 /
b1001111 .
1!
#840002
0!
#845002
b11 /
b1010000 .
1!
#850002
0!
#855002
b100 /
b1010001 .
1!
#860002
0!
#865002
b101 /
b1010010 .
1!
#870002
0!
#875002
b110 /
b1010011 .
1!
#880002
0!
#885002
b111 /
b1010100 .
1!
#890002
0!
#895002
b1000 /
b1010101 .
1!
#900002
0!
#905002
b1001 /
b1010110 .
1!
#910002
0!
#915002
b1010 /
b1010111 .
1!
#920002
0!
#925002
b1 '
b0 ,
1#
b0 /
b1011000 .
1!
#930002
0!
#935002
b1 &
b1 1
0#
b1 /
b1011001 .
1!
#940002
0!
#945002
b10 /
b1011010 .
1!
#950002
0!
#955002
b11 /
b1011011 .
1!
#960002
0!
#965002
b100 /
b1011100 .
1!
#970002
0!
#975002
b101 /
b1011101 .
1!
#980002
0!
#985002
b110 /
b1011110 .
1!
#990002
0!
#995002
b111 /
b1011111 .
1!
#1000002
0!
#1005002
b1000 /
b1100000 .
1!
#1010002
0!
#1015002
b1001 /
b1100001 .
1!
#1020002
0!
#1025002
b1010 /
b1100010 .
1!
#1030002
0!
#1035002
b10 '
b1 ,
1#
b0 /
b1100011 .
1!
#1040002
0!
#1045002
0#
b1 /
b1100100 .
b10 &
b10 1
1!
#1050002
0!
#1055002
b10 /
b1100101 .
1!
#1060002
0!
#1065002
b11 /
b1100110 .
1!
#1070002
0!
#1075002
b100 /
b1100111 .
1!
#1080002
0!
#1085002
b101 /
b1101000 .
1!
#1090002
0!
#1095002
b110 /
b1101001 .
1!
#1100002
0!
#1105002
b111 /
b1101010 .
1!
#1110002
0!
#1115002
b1000 /
b1101011 .
1!
#1120002
0!
#1125002
b1001 /
b1101100 .
1!
#1130002
0!
#1135002
b1010 /
b1101101 .
1!
#1140002
0!
#1145002
b11 '
b10 ,
1#
b0 /
b1101110 .
1!
#1150002
0!
#1155002
b100 &
b100 1
0#
b1 /
b1101111 .
1!
#1160002
0!
#1165002
b10 /
b1110000 .
1!
#1170002
0!
#1175002
b11 /
b1110001 .
1!
#1180002
0!
#1185002
b100 /
b1110010 .
1!
#1190002
0!
#1195002
b101 /
b1110011 .
1!
#1200002
0!
#1205002
b110 /
b1110100 .
1!
#1210002
0!
#1215002
b111 /
b1110101 .
1!
#1220002
0!
#1225002
b1000 /
b1110110 .
1!
#1230002
0!
#1235002
b1001 /
b1110111 .
1!
#1240002
0!
#1245002
b1010 /
b1111000 .
1!
#1250002
0!
#1255002
b0 '
b10 (
b11 ,
b1 -
1+
1#
b0 /
1$
b0 .
1!
#1260002
0!
#1265002
0+
b11 %
b11 2
0#
b1 /
0$
b1 .
b1000 &
b1000 1
0*
1!
#1270002
0!
#1275002
b10 /
b10 .
1!
#1280002
0!
#1285002
b11 /
b11 .
1!
#1290002
0!
#1295002
b100 /
b100 .
1!
#1300002
0!
#1305002
b101 /
b101 .
1!
#1310002
0!
#1315002
b110 /
b110 .
1!
#1320002
0!
#1325002
b111 /
b111 .
1!
#1330002
0!
#1335002
b1000 /
b1000 .
1!
#1340002
0!
#1345002
b1001 /
b1001 .
1!
#1350002
0!
#1355002
b1010 /
b1010 .
1!
#1360002
0!
#1365002
b1 '
b0 ,
1#
b0 /
b1011 .
1!
#1370002
0!
#1375002
b11111111 %
b11111111 2
1*
b1 &
b1 1
0#
b1 /
b1100 .
1!
#1380002
0!
#1385002
b10 /
b1101 .
1!
#1390002
0!
#1395002
b11 /
b1110 .
1!
#1400002
0!
#1405002
b100 /
b1111 .
1!
#1410002
0!
#1415002
b101 /
b10000 .
1!
#1420002
0!
#1425002
b110 /
b10001 .
1!
#1430002
0!
#1435002
b111 /
b10010 .
1!
#1440002
0!
#1445002
b1000 /
b10011 .
1!
#1450002
0!
#1455002
b1001 /
b10100 .
1!
#1460002
0!
#1465002
b1010 /
b10101 .
1!
#1470002
0!
#1475002
b10 '
b1 ,
1#
b0 /
b10110 .
1!
#1480002
0!
#1485002
0#
b1 /
b10111 .
b10 &
b10 1
1!
#1490002
0!
#1495002
b10 /
b11000 .
1!
#1500002
0!
#1505002
b11 /
b11001 .
1!
#1510002
0!
#1515002
b100 /
b11010 .
1!
#1520002
0!
#1525002
b101 /
b11011 .
1!
#1530002
0!
#1535002
b110 /
b11100 .
1!
#1540002
0!
#1545002
b111 /
b11101 .
1!
#1550002
0!
#1555002
b1000 /
b11110 .
1!
#1560002
0!
#1565002
b1001 /
b11111 .
1!
#1570002
0!
#1575002
b1010 /
b100000 .
1!
#1580002
0!
#1585002
b11 '
b10 ,
1#
b0 /
b100001 .
1!
#1590002
0!
#1595002
b100 &
b100 1
0#
b1 /
b100010 .
1!
#1600002
0!
#1605002
b10 /
b100011 .
1!
#1610002
0!
#1615002
b11 /
b100100 .
1!
#1620002
0!
#1625002
b100 /
b100101 .
1!
#1630002
0!
#1635002
b101 /
b100110 .
1!
#1640002
0!
#1645002
b110 /
b100111 .
1!
#1650002
0!
#1655002
b111 /
b101000 .
1!
#1660002
0!
#1665002
b1000 /
b101001 .
1!
#1670002
0!
#1675002
b1001 /
b101010 .
1!
#1680002
0!
#1685002
b1010 /
b101011 .
1!
#1690002
0!
#1695002
b0 '
b11 ,
1#
b0 /
b101100 .
1!
#1700002
0!
#1705002
b11 %
b11 2
0#
b1 /
b101101 .
b1000 &
b1000 1
0*
1!
#1710002
0!
#1715002
b10 /
b101110 .
1!
#1720002
0!
#1725002
b11 /
b101111 .
1!
#1730002
0!
#1735002
b100 /
b110000 .
1!
#1740002
0!
#1745002
b101 /
b110001 .
1!
#1750002
0!
#1755002
b110 /
b110010 .
1!
#1760002
0!
#1765002
b111 /
b110011 .
1!
#1770002
0!
#1775002
b1000 /
b110100 .
1!
#1780002
0!
#1785002
b1001 /
b110101 .
1!
#1790002
0!
#1795002
b1010 /
b110110 .
1!
#1800002
0!
#1805002
b1 '
b0 ,
1#
b0 /
b110111 .
1!
#1810002
0!
#1815002
b11111111 %
b11111111 2
1*
b1 &
b1 1
0#
b1 /
b111000 .
1!
#1820002
0!
#1825002
b10 /
b111001 .
1!
#1830002
0!
#1835002
b11 /
b111010 .
1!
#1840002
0!
#1845002
b100 /
b111011 .
1!
#1850002
0!
#1855002
b101 /
b111100 .
1!
#1860002
0!
#1865002
b110 /
b111101 .
1!
#1870002
0!
#1875002
b111 /
b111110 .
1!
#1880002
0!
#1885002
b1000 /
b111111 .
1!
#1890002
0!
#1895002
b1001 /
b1000000 .
1!
#1900002
0!
#1905002
b1010 /
b1000001 .
1!
#1910002
0!
#1915002
b10 '
b1 ,
1#
b0 /
b1000010 .
1!
#1920002
0!
#1925002
0#
b1 /
b1000011 .
b10 &
b10 1
1!
#1930002
0!
#1935002
b10 /
b1000100 .
1!
#1940002
0!
#1945002
b11 /
b1000101 .
1!
#1950002
0!
#1955002
b100 /
b1000110 .
1!
#1960002
0!
#1965002
b101 /
b1000111 .
1!
#1970002
0!
#1975002
b110 /
b1001000 .
1!
#1980002
0!
#1985002
b111 /
b1001001 .
1!
#1990002
0!
#1995002
b1000 /
b1001010 .
1!
#2000002
0!
#2005002
b1001 /
b1001011 .
1!
#2010002
0!
#2015002
b1010 /
b1001100 .
1!
#2020002
0!
#2025002
b11 '
b10 ,
1#
b0 /
b1001101 .
1!
#2030002
0!
#2035002
b100 &
b100 1
0#
b1 /
b1001110 .
1!
#2040002
0!
#2045002
b10 /
b1001111 .
1!
#2050002
0!
#2055002
b11 /
b1010000 .
1!
#2060002
0!
#2065002
b100 /
b1010001 .
1!
#2070002
0!
#2075002
b101 /
b1010010 .
1!
#2080002
0!
#2085002
b110 /
b1010011 .
1!
#2090002
0!
#2095002
b111 /
b1010100 .
1!
#2100002
0!
#2105002
b1000 /
b1010101 .
1!
#2110002
0!
#2115002
b1001 /
b1010110 .
1!
#2120002
0!
#2125002
b1010 /
b1010111 .
1!
#2130002
0!
#2135002
b0 '
b11 ,
1#
b0 /
b1011000 .
1!
#2140002
0!
#2145002
b11 %
b11 2
0#
b1 /
b1011001 .
b1000 &
b1000 1
0*
1!
#2150002
0!
#2155002
b10 /
b1011010 .
1!
#2160002
0!
#2165002
b11 /
b1011011 .
1!
#2170002
0!
#2175002
b100 /
b1011100 .
1!
#2180002
0!
#2185002
b101 /
b1011101 .
1!
#2190002
0!
#2195002
b110 /
b1011110 .
1!
#2200002
0!
#2205002
b111 /
b1011111 .
1!
#2210002
0!
#2215002
b1000 /
b1100000 .
1!
#2220002
0!
#2225002
b1001 /
b1100001 .
1!
#2230002
0!
#2235002
b1010 /
b1100010 .
1!
#2240002
0!
#2245002
b1 '
b0 ,
1#
b0 /
b1100011 .
1!
#2250002
0!
#2255002
b11111111 %
b11111111 2
1*
b1 &
b1 1
0#
b1 /
b1100100 .
1!
#2260002
0!
#2265002
b10 /
b1100101 .
1!
#2270002
0!
#2275002
b11 /
b1100110 .
1!
#2280002
0!
#2285002
b100 /
b1100111 .
1!
#2290002
0!
#2295002
b101 /
b1101000 .
1!
#2300002
0!
#2305002
b110 /
b1101001 .
1!
#2310002
0!
#2315002
b111 /
b1101010 .
1!
#2320002
0!
#2325002
b1000 /
b1101011 .
1!
#2330002
0!
#2335002
b1001 /
b1101100 .
1!
#2340002
0!
#2345002
b1010 /
b1101101 .
1!
#2350002
0!
#2355002
b10 '
b1 ,
1#
b0 /
b1101110 .
1!
#2360002
0!
#2365002
0#
b1 /
b1101111 .
b10 &
b10 1
1!
#2370002
0!
#2375002
b10 /
b1110000 .
1!
#2380002
0!
#2385002
b11 /
b1110001 .
1!
#2390002
0!
#2395002
b100 /
b1110010 .
1!
#2400002
0!
#2405002
b101 /
b1110011 .
1!
#2410002
0!
#2415002
b110 /
b1110100 .
1!
#2420002
0!
#2425002
b111 /
b1110101 .
1!
#2430002
0!
#2435002
b1000 /
b1110110 .
1!
#2440002
0!
#2445002
b1001 /
b1110111 .
1!
#2450002
0!
#2455002
b1010 /
b1111000 .
1!
#2460002
0!
#2465002
b11 '
b11 (
b10 ,
b10 -
1+
1#
b0 /
1$
b0 .
1!
#2470002
0!
#2475002
b11 %
b11 2
0+
0*
b100 &
b100 1
0#
b1 /
0$
b1 .
1!
#2480002
0!
#2485002
b10 /
b10 .
1!
#2490002
0!
#2495002
b11 /
b11 .
1!
#2500002
0!
#2505002
b100 /
b100 .
1!
#2510002
0!
#2515002
b101 /
b101 .
1!
#2520002
0!
#2525002
b110 /
b110 .
1!
#2530002
0!
#2535002
b111 /
b111 .
1!
#2540002
0!
#2545002
b1000 /
b1000 .
1!
#2550002
0!
